{
    "created_time": "2018-04-18T14:14:01Z",
    "files": [
        {
            "attachment_folder": "",
            "attachments": [
            ],
            "created_time": "2018-04-18T14:04:29Z",
            "modified_time": "2018-04-18T14:04:29Z",
            "name": "SGML风格 短标签.md"
        },
        {
            "attachment_folder": "",
            "attachments": [
            ],
            "created_time": "2018-04-18T14:14:39Z",
            "modified_time": "2018-04-18T14:14:39Z",
            "name": "ASP风格.md"
        },
        {
            "attachment_folder": "",
            "attachments": [
            ],
            "created_time": "2018-04-18T15:14:09Z",
            "modified_time": "2018-04-18T15:14:09Z",
            "name": "Script风格.md"
        }
    ],
    "sub_directories": [
    ],
    "version": "1"
}
